cpg2code/__init__.py
cpg2code/cpg2code_factory.py
cpg2code/symbolic_tracking.py
cpg2code/three_address_code_path.py
cpg2code-1.0.3.dist-info/AUTHORS.txt
cpg2code-1.0.3.dist-info/LICENSE.txt
cpg2code-1.0.3.dist-info/METADATA
cpg2code-1.0.3.dist-info/WHEEL
cpg2code-1.0.3.dist-info/top_level.txt
cpg2code-1.0.3.dist-info/zip-safe
cpg2code-1.0.3.dist-info/RECORD
