Metadata-Version: 2.1
Name: cpg2code
Version: 1.0.3
Summary: enhanced phpjoern framework helping library for cpg2code and symbolic tracking.
Home-page: UNKNOWN
Author: shaobaobaoer
Author-email: shaobaobaoer@126.com
License: New BSD
Keywords: click plugin setuptools entry-point
Platform: UNKNOWN
Classifier: Topic :: Utilities
Classifier: Intended Audience :: Developers
Classifier: Development Status :: 5 - Production/Stable
Classifier: License :: OSI Approved :: BSD License
Classifier: Programming Language :: Python
Classifier: Programming Language :: Python :: 3
License-File: LICENSE.txt
License-File: AUTHORS.txt
Requires-Dist: pjscan
Requires-Dist: py2neo
Requires-Dist: networkx
Requires-Dist: Levenshtein
Requires-Dist: pandas
Requires-Dist: ruamel.yaml
Requires-Dist: matplotlib
